c0banAPI/__init__.py
c0banAPI/api.py
c0banAPI/tradingapi.py
c0banAPI-1.5.dist-info/LICENSE.txt
c0banAPI-1.5.dist-info/METADATA
c0banAPI-1.5.dist-info/WHEEL
c0banAPI-1.5.dist-info/top_level.txt
c0banAPI-1.5.dist-info/RECORD
