Metadata-Version: 2.1
Name: c0banAPI
Version: 1.5
Summary: c0banAPI will request c0ban blockchain insight api to get blocks and transactions related data
Home-page: https://github.com/dc-aichara/c0banAPI
Author: Dayal Chand Aichara
Author-email: dc.aichara@gmail.com
License: MIT
Download-URL: https://github.com/dc-aichara/c0banAPI/archive/v-1.5.tar.gz
Keywords: c0ban,blockchain,cryptocurrency,blocks,c0bantrade,c0banPrice
Platform: UNKNOWN
Classifier: Development Status :: 5 - Production/Stable
Classifier: Intended Audience :: Science/Research
Classifier: Topic :: Software Development :: Build Tools
Classifier: License :: OSI Approved :: MIT License
Classifier: Programming Language :: Python :: 3
Classifier: Programming Language :: Python :: 3.3
Classifier: Programming Language :: Python :: 3.5
Classifier: Programming Language :: Python :: 3.6
Classifier: Programming Language :: Python :: 3.7
Classifier: Operating System :: OS Independent
Requires-Dist: requests
Requires-Dist: pandas
